README.md
setup.py
atasker/__init__.py
atasker/co.py
atasker/f.py
atasker/supervisor.py
atasker/threads.py
atasker/workers.py
atasker.egg-info/PKG-INFO
atasker.egg-info/SOURCES.txt
atasker.egg-info/dependency_links.txt
atasker.egg-info/requires.txt
atasker.egg-info/top_level.txt