Metadata-Version: 2.1
Name: atasker
Version: 0.7.9
Summary: Thread and multiprocessing pooling, task processing via asyncio
Home-page: https://github.com/alttch/atasker
Author: Altertech
Author-email: div@altertech.com
License: Apache License 2.0
Platform: UNKNOWN
Classifier: Programming Language :: Python :: 3
Classifier: License :: OSI Approved :: Apache Software License
Classifier: Topic :: Software Development :: Libraries
